{
  "game_id": "hp",
  "exe_match": ".*theHunterCotW.*",
  "archive_version": 3,
  "file_hash_size": 4,
  "oo_decompress_dll": false,
  "area_prefixes": [
    "",
    "globalhires_",
    "hp_germany_farmland_fall_",
    "hp_pacific_northwest_",
    "hp_siberia_",
    "hp_africa_",
    "hp_patagonia_",
    "hp_trophyworld_",
    "hp_yukon_",
    "hp_trophyworld_2_",
    "hp_iberia_"
  ],
  "world_indexes": [0,1,2,3],
  "world_patches": [
    "terrain/hp/patches/",
    "terrain/jc3/patches/",
    "worlds/base/terrain/hp/patches/",
    "worlds/world${WORLD_INDEX}/terrain/world${WORLD_INDEX}/patches/"
  ],
  "world_occluders": [
    "terrain/hp/occluder/",
    "terrain/jc3/occluder/",
    "worlds/base/terrain/hp/occluder/",
    "worlds/world0/terrain/world${WORLD_INDEX}/occluder/"
  ],
  "world_navheightfields": [
    "terrain/hp/navheightfield/globalhires/",
    "terrain/jc3/navheightfield/globalhires/",
    "worlds/base/terrain/hp/navheightfield/globalhires/",
    "worlds/world0/terrain/world${WORLD_INDEX}/navheightfield/globalhires/"
  ],
  "world_hm": [
    "terrain/hp/horizonmap/horizon_",
    "terrain/jc3/horizonmap/horizon_",
    "worlds/base/terrain/hp/horizonmap/horizon_hp_${AREA_PREFIX}",
    "worlds/world${WORLD_INDEX}/terrain/world${WORLD_INDEX}/horizonmap/horizon_hp_${AREA_PREFIX}"
  ],
  "world_ai": [
    "ai/tiles/",
    "worlds/base/ai/tiles/",
    "worlds/world${WORLD_INDEX}/ai/tiles/"
  ],
  "map_zooms": [0,1,2,3],
  "map_max_count": 500,
  "map_prefixes": [
    "textures/ui/map_reserve_0/",
    "textures/ui/map_reserve_1/",
    "textures/ui/map_reserve_2/",
    "textures/ui/map_reserve_3/",
    "textures/ui/map_reserve_4/",
    "textures/ui/map_reserve_5/",
    "textures/ui/map_reserve_6/",
    "textures/ui/map_reserve_7/",
    "textures/ui/map_reserve_8/",
    "textures/ui/map_reserve_9/"
  ],
  "unarchived_files": [],
  "archive_paths": [
    "${GAME_DIR}/archives_win64/"
  ],
  "mdic_ftype": "mdi",
  "navmesh_ftype": "h2014",
  "obc_ftype": "",
  "pfs_ftype": "pfx",
  "has_garcs": false,
  "file_assoc": [
    {
      ".ee": "sarc",
      ".epe": "rtpc"
    },
    {
      ".bl": "sarc",
      ".nl": "sarc",
      ".fl": "sarc",
      ".blo": "rtpc",
      ".nl.mdic": "mdi",
      ".fl.mdic": "mdi",
      ".pfs": "pfx",
      ".obc": "obc"
    },
    {
      ".meshc": "adf",
      ".hrmeshc": "adf",
      ".modelc": "adf",
      ".model_deps": "txt",
      ".pfxc": "pfx"
    },
    {
      ".ddsc": "avtx,dds",
      ".hmddsc": "atx,META-NO-TYPE"
    },
    {
      ".fmod_sbankc": "txt",
      ".fmod_bankc": "riff"
    },
    {
      ".swf": "gfx",
      ".cfx": "gfx",
      ".gfx": "gfx"
    }
  ]
}